ascicolor/__init__.py
ascicolor/test.py
ascicolor-4.3.dist-info/METADATA
ascicolor-4.3.dist-info/WHEEL
ascicolor-4.3.dist-info/top_level.txt
ascicolor-4.3.dist-info/RECORD
