Metadata-Version: 2.1
Name: ascicolor
Version: 4.3
Summary: Make Your Code colrful
Author-email: ascdev@gmail.com
License: Eclipse Public License 2.0
